smart_web_screenshot/__init__.py
smart_web_screenshot/smart_screenshot.py
smart_web_screenshot/test.py
smart_web_screenshot-1.2.4.dist-info/METADATA
smart_web_screenshot-1.2.4.dist-info/WHEEL
smart_web_screenshot-1.2.4.dist-info/top_level.txt
smart_web_screenshot-1.2.4.dist-info/RECORD
