Metadata-Version: 2.1
Name: smart-web-screenshot
Version: 1.2.4
Summary: A smart web screenshot taker that is designed to bypass several issues commonly faced by scapers
Home-page: https://github.com/wasimsurjo/smart_web_screenshot
Author: Wasim Surjo
Author-email: wasimmiller55@gmail.com
License: MIT
Platform: UNKNOWN
Classifier: Programming Language :: Python :: 3
Classifier: Operating System :: OS Independent
Requires-Python: >=3.6
Requires-Dist: requests
Requires-Dist: selenium
Requires-Dist: selenium-stealth
Requires-Dist: undetected-chromedriver
Requires-Dist: webdriver-manager
